ampliomws-0.7.5.dist-info/DESCRIPTION.rst
ampliomws-0.7.5.dist-info/METADATA
ampliomws-0.7.5.dist-info/RECORD
ampliomws-0.7.5.dist-info/WHEEL
ampliomws-0.7.5.dist-info/metadata.json
ampliomws-0.7.5.dist-info/top_level.txt
mws/__init__.py
mws/mws.py
mws/offamazonpayments.py
mws/utils.py
